multilevel_mesa/__init__.py
multilevel_mesa/multilevel_mesa.py
multilevel_mesa-0.0.2.dist-info/LICENSE
multilevel_mesa-0.0.2.dist-info/METADATA
multilevel_mesa-0.0.2.dist-info/WHEEL
multilevel_mesa-0.0.2.dist-info/top_level.txt
multilevel_mesa-0.0.2.dist-info/RECORD
